var ingenio = {
"type": "FeatureCollection",
"name": "ingenio",
"crs": { "type": "name", "properties": { "name": "urn:ogc:def:crs:OGC:1.3:CRS84" } },
"features": [
{ "type": "Feature", "properties": { "Coord": "19.65457564198762, -102.48757621991358", "Nombre": "Ingenio Santa Clara", "Lat": 19.654575641987599, "Long": -102.487576219913 }, "geometry": { "type": "Point", "coordinates": [ -102.487576219912995, 19.654575641987599 ] } },
{ "type": "Feature", "properties": { "Coord": "18.611494954146398, -95.52545789508882", "Nombre": "Ingenio San Pedro", "Lat": 18.611494954146298, "Long": -95.525457895088806 }, "geometry": { "type": "Point", "coordinates": [ -95.525457895088806, 18.611494954146298 ] } }
]
}
